{
    "1": {
        "Id": "1",
        "Date": "27/01/1922",
        "heure": "01:10",
        "NMRe(m)": "0.357",
        "Maree(m)": "0.86",
        "Surcote(m)": "0.14",
        "Hs(vagues)(m)": "4.35",
        "Tp(vagues)(s)": "18.62",
        "Dp(vagues)()": "259.97",
        "U(vent)(m)": "9.76",
        "Dir(vent)()": "178.21",
        "Qualite(surcote)": "-99",
        "Qualite(vagues)": "-99",
        "Qualite(vent)": "-99"
    },
    "2": {
        "Id": "2",
        "Date": "27/01/1922",
        "heure": "01:20",
        "NMRe(m)": "0.357",
        "Maree(m)": "0.96",
        "Surcote(m)": "0.15",
        "Hs(vagues)(m)": "4.34",
        "Tp(vagues)(s)": "18.59",
        "Dp(vagues)()": "259.95",
        "U(vent)(m)": "9.86",
        "Dir(vent)()": "177.95",
        "Qualite(surcote)": "-99",
        "Qualite(vagues)": "-99",
        "Qualite(vent)": "-99"
    },
    "3": {
        "Id": "3",
        "Date": "27/01/1922",
        "heure": "01:30",
        "NMRe(m)": "0.357",
        "Maree(m)": "1.06",
        "Surcote(m)": "0.15",
        "Hs(vagues)(m)": "4.33",
        "Tp(vagues)(s)": "18.56",
        "Dp(vagues)()": "259.92",
        "U(vent)(m)": "9.95",
        "Dir(vent)()": "177.68",
        "Qualite(surcote)": "-99",
        "Qualite(vagues)": "-99",
        "Qualite(vent)": "-99"
    },
    "4": {
        "Id": "4",
        "Date": "27/01/1922",
        "heure": "01:40",
        "NMRe(m)": "0.357",
        "Maree(m)": "1.15",
        "Surcote(m)": "0.15",
        "Hs(vagues)(m)": "4.32",
        "Tp(vagues)(s)": "18.53",
        "Dp(vagues)()": "259.90",
        "U(vent)(m)": "10.05",
        "Dir(vent)()": "177.41",
        "Qualite(surcote)": "-99",
        "Qualite(vagues)": "-99",
        "Qualite(vent)": "-99"
    },
    "5": {
        "Id": "5",
        "Date": "27/01/1922",
        "heure": "01:50",
        "NMRe(m)": "0.357",
        "Maree(m)": "1.23",
        "Surcote(m)": "0.16",
        "Hs(vagues)(m)": "4.31",
        "Tp(vagues)(s)": "18.50",
        "Dp(vagues)()": "259.87",
        "U(vent)(m)": "10.14",
        "Dir(vent)()": "177.15",
        "Qualite(surcote)": "-99",
        "Qualite(vagues)": "-99",
        "Qualite(vent)": "-99"
    },
    "6": {
        "Id": "6",
        "Date": "27/01/1922",
        "heure": "02:00",
        "NMRe(m)": "0.357",
        "Maree(m)": "1.31",
        "Surcote(m)": "0.16",
        "Hs(vagues)(m)": "4.31",
        "Tp(vagues)(s)": "18.47",
        "Dp(vagues)()": "259.85",
        "U(vent)(m)": "10.24",
        "Dir(vent)()": "176.88",
        "Qualite(surcote)": "-99",
        "Qualite(vagues)": "-99",
        "Qualite(vent)": "-99"
    },
    "7": {
        "Id": "7",
        "Date": "27/01/1922",
        "heure": "02:10",
        "NMRe(m)": "0.357",
        "Maree(m)": "1.38",
        "Surcote(m)": "0.16",
        "Hs(vagues)(m)": "4.30",
        "Tp(vagues)(s)": "18.44",
        "Dp(vagues)()": "259.82",
        "U(vent)(m)": "10.34",
        "Dir(vent)()": "176.61",
        "Qualite(surcote)": "-99",
        "Qualite(vagues)": "-99",
        "Qualite(vent)": "-99"
    },
    "8": {
        "Id": "8",
        "Date": "27/01/1922",
        "heure": "02:20",
        "NMRe(m)": "0.357",
        "Maree(m)": "1.44",
        "Surcote(m)": "0.17",
        "Hs(vagues)(m)": "4.29",
        "Tp(vagues)(s)": "18.41",
        "Dp(vagues)()": "259.80",
        "U(vent)(m)": "10.43",
        "Dir(vent)()": "176.35",
        "Qualite(surcote)": "-99",
        "Qualite(vagues)": "-99",
        "Qualite(vent)": "-99"
    },
    "9": {
        "Id": "9",
        "Date": "27/01/1922",
        "heure": "02:30",
        "NMRe(m)": "0.357",
        "Maree(m)": "1.50",
        "Surcote(m)": "0.17",
        "Hs(vagues)(m)": "4.28",
        "Tp(vagues)(s)": "18.38",
        "Dp(vagues)()": "259.77",
        "U(vent)(m)": "10.53",
        "Dir(vent)()": "176.08",
        "Qualite(surcote)": "-99",
        "Qualite(vagues)": "-99",
        "Qualite(vent)": "-99"
    },
    "10": {
        "Id": "10",
        "Date": "27/01/1922",
        "heure": "02:40",
        "NMRe(m)": "0.357",
        "Maree(m)": "1.55",
        "Surcote(m)": "0.17",
        "Hs(vagues)(m)": "4.27",
        "Tp(vagues)(s)": "18.35",
        "Dp(vagues)()": "259.75",
        "U(vent)(m)": "10.62",
        "Dir(vent)()": "175.81",
        "Qualite(surcote)": "-99",
        "Qualite(vagues)": "-99",
        "Qualite(vent)": "-99"
    },
    "11": {
        "Id": "11",
        "Date": "27/01/1922",
        "heure": "02:50",
        "NMRe(m)": "0.357",
        "Maree(m)": "1.59",
        "Surcote(m)": "0.18",
        "Hs(vagues)(m)": "4.27",
        "Tp(vagues)(s)": "18.32",
        "Dp(vagues)()": "259.72",
        "U(vent)(m)": "10.72",
        "Dir(vent)()": "175.55",
        "Qualite(surcote)": "-99",
        "Qualite(vagues)": "-99",
        "Qualite(vent)": "-99"
    },
    "12": {
        "Id": "12",
        "Date": "27/01/1922",
        "heure": "03:00",
        "NMRe(m)": "0.357",
        "Maree(m)": "1.62",
        "Surcote(m)": "0.18",
        "Hs(vagues)(m)": "4.26",
        "Tp(vagues)(s)": "18.29",
        "Dp(vagues)()": "259.70",
        "U(vent)(m)": "10.82",
        "Dir(vent)()": "175.28",
        "Qualite(surcote)": "-99",
        "Qualite(vagues)": "-99",
        "Qualite(vent)": "-99"
    },
    "13": {
        "Id": "13",
        "Date": "27/01/1922",
        "heure": "03:10",
        "NMRe(m)": "0.357",
        "Maree(m)": "1.64",
        "Surcote(m)": "0.19",
        "Hs(vagues)(m)": "4.25",
        "Tp(vagues)(s)": "18.26",
        "Dp(vagues)()": "259.67",
        "U(vent)(m)": "10.91",
        "Dir(vent)()": "175.01",
        "Qualite(surcote)": "-99",
        "Qualite(vagues)": "-99",
        "Qualite(vent)": "-99"
    },
    "14": {
        "Id": "14",
        "Date": "27/01/1922",
        "heure": "03:20",
        "NMRe(m)": "0.357",
        "Maree(m)": "1.66",
        "Surcote(m)": "0.19",
        "Hs(vagues)(m)": "4.24",
        "Tp(vagues)(s)": "18.23",
        "Dp(vagues)()": "259.64",
        "U(vent)(m)": "11.01",
        "Dir(vent)()": "174.75",
        "Qualite(surcote)": "-99",
        "Qualite(vagues)": "-99",
        "Qualite(vent)": "-99"
    },
    "15": {
        "Id": "15",
        "Date": "27/01/1922",
        "heure": "03:30",
        "NMRe(m)": "0.357",
        "Maree(m)": "1.67",
        "Surcote(m)": "0.19",
        "Hs(vagues)(m)": "4.23",
        "Tp(vagues)(s)": "18.20",
        "Dp(vagues)()": "259.62",
        "U(vent)(m)": "11.10",
        "Dir(vent)()": "174.48",
        "Qualite(surcote)": "-99",
        "Qualite(vagues)": "-99",
        "Qualite(vent)": "-99"
    },
    "16": {
        "Id": "16",
        "Date": "27/01/1922",
        "heure": "03:40",
        "NMRe(m)": "0.357",
        "Maree(m)": "1.66",
        "Surcote(m)": "0.20",
        "Hs(vagues)(m)": "4.23",
        "Tp(vagues)(s)": "18.17",
        "Dp(vagues)()": "259.59",
        "U(vent)(m)": "11.20",
        "Dir(vent)()": "174.21",
        "Qualite(surcote)": "-99",
        "Qualite(vagues)": "-99",
        "Qualite(vent)": "-99"
    },
    "17": {
        "Id": "17",
        "Date": "27/01/1922",
        "heure": "03:50",
        "NMRe(m)": "0.357",
        "Maree(m)": "1.65",
        "Surcote(m)": "0.20",
        "Hs(vagues)(m)": "4.22",
        "Tp(vagues)(s)": "18.14",
        "Dp(vagues)()": "259.57",
        "U(vent)(m)": "11.30",
        "Dir(vent)()": "173.95",
        "Qualite(surcote)": "-99",
        "Qualite(vagues)": "-99",
        "Qualite(vent)": "-99"
    },
    "18": {
        "Id": "18",
        "Date": "27/01/1922",
        "heure": "04:00",
        "NMRe(m)": "0.357",
        "Maree(m)": "1.63",
        "Surcote(m)": "0.20",
        "Hs(vagues)(m)": "4.21",
        "Tp(vagues)(s)": "18.11",
        "Dp(vagues)()": "259.54",
        "U(vent)(m)": "11.39",
        "Dir(vent)()": "173.68",
        "Qualite(surcote)": "-99",
        "Qualite(vagues)": "-99",
        "Qualite(vent)": "-99"
    },
    "19": {
        "Id": "19",
        "Date": "27/01/1922",
        "heure": "04:10",
        "NMRe(m)": "0.357",
        "Maree(m)": "1.60",
        "Surcote(m)": "0.21",
        "Hs(vagues)(m)": "4.20",
        "Tp(vagues)(s)": "18.07",
        "Dp(vagues)()": "259.52",
        "U(vent)(m)": "11.49",
        "Dir(vent)()": "173.41",
        "Qualite(surcote)": "-99",
        "Qualite(vagues)": "-99",
        "Qualite(vent)": "-99"
    },
    "20": {
        "Id": "20",
        "Date": "27/01/1922",
        "heure": "04:20",
        "NMRe(m)": "0.357",
        "Maree(m)": "1.56",
        "Surcote(m)": "0.21",
        "Hs(vagues)(m)": "4.19",
        "Tp(vagues)(s)": "18.04",
        "Dp(vagues)()": "259.49",
        "U(vent)(m)": "11.59",
        "Dir(vent)()": "173.15",
        "Qualite(surcote)": "-99",
        "Qualite(vagues)": "-99",
        "Qualite(vent)": "-99"
    },
    "21": {
        "Id": "21",
        "Date": "27/01/1922",
        "heure": "04:30",
        "NMRe(m)": "0.357",
        "Maree(m)": "1.50",
        "Surcote(m)": "0.21",
        "Hs(vagues)(m)": "4.19",
        "Tp(vagues)(s)": "18.01",
        "Dp(vagues)()": "259.47",
        "U(vent)(m)": "11.68",
        "Dir(vent)()": "172.88",
        "Qualite(surcote)": "-99",
        "Qualite(vagues)": "-99",
        "Qualite(vent)": "-99"
    },
    "22": {
        "Id": "22",
        "Date": "27/01/1922",
        "heure": "04:40",
        "NMRe(m)": "0.357",
        "Maree(m)": "1.44",
        "Surcote(m)": "0.22",
        "Hs(vagues)(m)": "4.18",
        "Tp(vagues)(s)": "17.98",
        "Dp(vagues)()": "259.44",
        "U(vent)(m)": "11.78",
        "Dir(vent)()": "172.61",
        "Qualite(surcote)": "-99",
        "Qualite(vagues)": "-99",
        "Qualite(vent)": "-99"
    },
    "23": {
        "Id": "23",
        "Date": "27/01/1922",
        "heure": "04:50",
        "NMRe(m)": "0.357",
        "Maree(m)": "1.37",
        "Surcote(m)": "0.22",
        "Hs(vagues)(m)": "4.17",
        "Tp(vagues)(s)": "17.95",
        "Dp(vagues)()": "259.42",
        "U(vent)(m)": "11.87",
        "Dir(vent)()": "172.35",
        "Qualite(surcote)": "-99",
        "Qualite(vagues)": "-99",
        "Qualite(vent)": "-99"
    },
    "24": {
        "Id": "24",
        "Date": "27/01/1922",
        "heure": "05:00",
        "NMRe(m)": "0.357",
        "Maree(m)": "1.29",
        "Surcote(m)": "0.22",
        "Hs(vagues)(m)": "4.16",
        "Tp(vagues)(s)": "17.92",
        "Dp(vagues)()": "259.39",
        "U(vent)(m)": "11.97",
        "Dir(vent)()": "172.08",
        "Qualite(surcote)": "-99",
        "Qualite(vagues)": "-99",
        "Qualite(vent)": "-99"
    },
    "25": {
        "Id": "25",
        "Date": "27/01/1922",
        "heure": "05:10",
        "NMRe(m)": "0.357",
        "Maree(m)": "1.19",
        "Surcote(m)": "0.23",
        "Hs(vagues)(m)": "4.15",
        "Tp(vagues)(s)": "17.89",
        "Dp(vagues)()": "259.36",
        "U(vent)(m)": "12.07",
        "Dir(vent)()": "171.81",
        "Qualite(surcote)": "-99",
        "Qualite(vagues)": "-99",
        "Qualite(vent)": "-99"
    },
    "26": {
        "Id": "26",
        "Date": "27/01/1922",
        "heure": "05:20",
        "NMRe(m)": "0.357",
        "Maree(m)": "1.09",
        "Surcote(m)": "0.23",
        "Hs(vagues)(m)": "4.14",
        "Tp(vagues)(s)": "17.86",
        "Dp(vagues)()": "259.34",
        "U(vent)(m)": "12.16",
        "Dir(vent)()": "171.55",
        "Qualite(surcote)": "-99",
        "Qualite(vagues)": "-99",
        "Qualite(vent)": "-99"
    },
    "27": {
        "Id": "27",
        "Date": "27/01/1922",
        "heure": "05:30",
        "NMRe(m)": "0.357",
        "Maree(m)": "0.97",
        "Surcote(m)": "0.23",
        "Hs(vagues)(m)": "4.14",
        "Tp(vagues)(s)": "17.83",
        "Dp(vagues)()": "259.31",
        "U(vent)(m)": "12.26",
        "Dir(vent)()": "171.28",
        "Qualite(surcote)": "-99",
        "Qualite(vagues)": "-99",
        "Qualite(vent)": "-99"
    },
    "28": {
        "Id": "28",
        "Date": "27/01/1922",
        "heure": "05:40",
        "NMRe(m)": "0.357",
        "Maree(m)": "0.85",
        "Surcote(m)": "0.24",
        "Hs(vagues)(m)": "4.13",
        "Tp(vagues)(s)": "17.80",
        "Dp(vagues)()": "259.29",
        "U(vent)(m)": "12.35",
        "Dir(vent)()": "171.01",
        "Qualite(surcote)": "-99",
        "Qualite(vagues)": "-99",
        "Qualite(vent)": "-99"
    },
    "29": {
        "Id": "29",
        "Date": "27/01/1922",
        "heure": "05:50",
        "NMRe(m)": "0.357",
        "Maree(m)": "0.72",
        "Surcote(m)": "0.24",
        "Hs(vagues)(m)": "4.12",
        "Tp(vagues)(s)": "17.77",
        "Dp(vagues)()": "259.26",
        "U(vent)(m)": "12.45",
        "Dir(vent)()": "170.75",
        "Qualite(surcote)": "-99",
        "Qualite(vagues)": "-99",
        "Qualite(vent)": "-99"
    },
    "30": {
        "Id": "30",
        "Date": "27/01/1922",
        "heure": "06:00",
        "NMRe(m)": "0.357",
        "Maree(m)": "0.58",
        "Surcote(m)": "0.25",
        "Hs(vagues)(m)": "4.11",
        "Tp(vagues)(s)": "17.74",
        "Dp(vagues)()": "259.24",
        "U(vent)(m)": "12.55",
        "Dir(vent)()": "170.48",
        "Qualite(surcote)": "-99",
        "Qualite(vagues)": "-99",
        "Qualite(vent)": "-99"
    },
    "31": {
        "Id": "31",
        "Date": "27/01/1922",
        "heure": "06:10",
        "NMRe(m)": "0.357",
        "Maree(m)": "0.43",
        "Surcote(m)": "0.25",
        "Hs(vagues)(m)": "4.12",
        "Tp(vagues)(s)": "17.72",
        "Dp(vagues)()": "259.27",
        "U(vent)(m)": "12.46",
        "Dir(vent)()": "171.67",
        "Qualite(surcote)": "-99",
        "Qualite(vagues)": "-99",
        "Qualite(vent)": "-99"
    },
    "32": {
        "Id": "32",
        "Date": "27/01/1922",
        "heure": "06:20",
        "NMRe(m)": "0.357",
        "Maree(m)": "0.28",
        "Surcote(m)": "0.25",
        "Hs(vagues)(m)": "4.12",
        "Tp(vagues)(s)": "17.71",
        "Dp(vagues)()": "259.31",
        "U(vent)(m)": "12.37",
        "Dir(vent)()": "172.87",
        "Qualite(surcote)": "-99",
        "Qualite(vagues)": "-99",
        "Qualite(vent)": "-99"
    },
    "33": {
        "Id": "33",
        "Date": "27/01/1922",
        "heure": "06:30",
        "NMRe(m)": "0.357",
        "Maree(m)": "0.12",
        "Surcote(m)": "0.25",
        "Hs(vagues)(m)": "4.13",
        "Tp(vagues)(s)": "17.69",
        "Dp(vagues)()": "259.34",
        "U(vent)(m)": "12.29",
        "Dir(vent)()": "174.06",
        "Qualite(surcote)": "-99",
        "Qualite(vagues)": "-99",
        "Qualite(vent)": "-99"
    },
    "34": {
        "Id": "34",
        "Date": "27/01/1922",
        "heure": "06:40",
        "NMRe(m)": "0.357",
        "Maree(m)": "-0.04",
        "Surcote(m)": "0.26",
        "Hs(vagues)(m)": "4.13",
        "Tp(vagues)(s)": "17.67",
        "Dp(vagues)()": "259.38",
        "U(vent)(m)": "12.20",
        "Dir(vent)()": "175.26",
        "Qualite(surcote)": "-99",
        "Qualite(vagues)": "-99",
        "Qualite(vent)": "-99"
    },
    "35": {
        "Id": "35",
        "Date": "27/01/1922",
        "heure": "06:50",
        "NMRe(m)": "0.357",
        "Maree(m)": "-0.20",
        "Surcote(m)": "0.26",
        "Hs(vagues)(m)": "4.13",
        "Tp(vagues)(s)": "17.65",
        "Dp(vagues)()": "259.41",
        "U(vent)(m)": "12.12",
        "Dir(vent)()": "176.45",
        "Qualite(surcote)": "-99",
        "Qualite(vagues)": "-99",
        "Qualite(vent)": "-99"
    },
    "36": {
        "Id": "36",
        "Date": "27/01/1922",
        "heure": "07:00",
        "NMRe(m)": "0.357",
        "Maree(m)": "-0.37",
        "Surcote(m)": "0.26",
        "Hs(vagues)(m)": "4.14",
        "Tp(vagues)(s)": "17.63",
        "Dp(vagues)()": "259.45",
        "U(vent)(m)": "12.03",
        "Dir(vent)()": "177.64",
        "Qualite(surcote)": "-99",
        "Qualite(vagues)": "-99",
        "Qualite(vent)": "-99"
    }
}